[{"time": "08:00", "className": "Physics", "date": "2021-09-02", "status": "Timed Out: Couldn't Find Join With Computer Audio Button or The Host Didn't Allow Entry"}, {"time": "08:00", "className": "Physics", "date": "2021-09-02", "status": "Timed Out: Couldn't Find Join With Computer Audio Button or The Host Didn't Allow Entry"}, {"time": "08:00", "className": "Physics", "date": "2021-09-02", "status": "Timed Out: Couldn't Find Join With Computer Audio Button or The Host Didn't Allow Entry"}, {"time": "10:30", "className": "Physics", "date": "2021-09-07", "status": "Success"}, {"time": "08:50", "className": "Chemistry", "date": "2021-09-13", "status": "Success"}, {"time": "10:30", "className": "Physics", "date": "2021-09-13", "status": "Success"}, {"time": "11:20", "className": "Computer Science", "date": "2021-09-13", "status": "Success"}, {"time": "12:10", "className": "Maths", "date": "2021-09-13", "status": "Success"}]